twitter_threader/__init__.py
twitter_threader/threader.py
twitter_threader-1.5.1.dist-info/LICENSE
twitter_threader-1.5.1.dist-info/WHEEL
twitter_threader-1.5.1.dist-info/METADATA
twitter_threader-1.5.1.dist-info/RECORD
