Metadata-Version: 2.1
Name: twitter_threader
Version: 1.5.1
Summary: Twitter Threader is a library to manage threads on Twitter. You can GET and POST threads on Twitter
Author-email: Iyanuoluwa Ajao <me@iyanuashiri.com>
Classifier: License :: OSI Approved :: MIT License
Project-URL: Home, https://github.com/iyanuashiri/twitter-threader
